pygal_maps_se/__init__.py
pygal_maps_se/maps.py
pygal_maps_se/se.lan.svg
pygal_maps_se-0.0.1.dist-info/LICENSE
pygal_maps_se-0.0.1.dist-info/METADATA
pygal_maps_se-0.0.1.dist-info/WHEEL
pygal_maps_se-0.0.1.dist-info/entry_points.txt
pygal_maps_se-0.0.1.dist-info/top_level.txt
pygal_maps_se-0.0.1.dist-info/RECORD
