Metadata-Version: 2.1
Name: pygal-maps-se
Version: 0.0.1
Summary: Swedish lan map for pygal
Home-page: http://pygal.org/
Author: Johan Vingbäck
Author-email: j.vingback@gmail.com
License: GNU LGPL v3+
Keywords: svg,chart,graph,maps,sweden
Platform: Any
Classifier: Environment :: Console
Classifier: Intended Audience :: End Users/Desktop
Classifier: License :: OSI Approved :: GNU Lesser General Public License v3 or later (LGPLv3+)
Classifier: Operating System :: OS Independent
Classifier: Programming Language :: Python :: 2
Classifier: Programming Language :: Python :: 3
Classifier: Topic :: Multimedia :: Graphics :: Presentation
Provides: pygal_maps_se
Requires-Dist: pygal (>=1.9.9)
